checkon_trial/checkon_trial.py
checkon_trial-0.0.3.dist-info/METADATA
checkon_trial-0.0.3.dist-info/WHEEL
checkon_trial-0.0.3.dist-info/entry_points.txt
checkon_trial-0.0.3.dist-info/top_level.txt
checkon_trial-0.0.3.dist-info/RECORD
